SecretChord/__init__.py
SecretChord/_base.py
SecretChord/_elements.py
SecretChord-0.0.1.dist-info/LICENSE
SecretChord-0.0.1.dist-info/METADATA
SecretChord-0.0.1.dist-info/WHEEL
SecretChord-0.0.1.dist-info/top_level.txt
SecretChord-0.0.1.dist-info/RECORD
