Metadata-Version: 2.1
Name: SecretChord
Version: 0.0.1
Summary: generate robust and beautiful Chord Diagrams
Home-page: https://github.com/secretBiology/SecretChord
Author: Rohit Suratekar
Author-email: rohitsuratekar@gmail.com
License: MIT License
Platform: UNKNOWN
Classifier: Programming Language :: Python :: 3.8
Classifier: License :: OSI Approved :: MIT License
Classifier: Operating System :: OS Independent
Requires-Dist: numpy
Requires-Dist: matplotlib
Requires-Dist: SecretColors
